chartsworth/__init__.py
chartsworth/client.py
chartsworth/emojis.py
chartsworth/plot.py
chartsworth-0.12.0.dist-info/LICENSE
chartsworth-0.12.0.dist-info/METADATA
chartsworth-0.12.0.dist-info/WHEEL
chartsworth-0.12.0.dist-info/RECORD
